djangocms_pai_banners/__init__.py
djangocms_pai_banners/admin.py
djangocms_pai_banners/apps.py
djangocms_pai_banners/models.py
djangocms_pai_banners/serializers.py
djangocms_pai_banners/tests.py
djangocms_pai_banners/urls.py
djangocms_pai_banners/views.py
djangocms_pai_banners/migrations/0001_initial.py
djangocms_pai_banners/migrations/__init__.py
djangocms_pai_banners-0.0.1.dist-info/AUTHORS.rst
djangocms_pai_banners-0.0.1.dist-info/LICENSE.txt
djangocms_pai_banners-0.0.1.dist-info/METADATA
djangocms_pai_banners-0.0.1.dist-info/WHEEL
djangocms_pai_banners-0.0.1.dist-info/top_level.txt
djangocms_pai_banners-0.0.1.dist-info/RECORD
